{
  "date": "2026-7-21",
  "max_level": 2,
  "pages_total": 22,
  "pages_ok": 22,
  "pages_retry": 0,
  "pages_fix": 0,
  "pages_error": 0,
  "details": [
    {
      "url": "https://cp.titan007.com/buy/JingCai.aspx?typeID=101&oddstype=2&date=2026-7-21",
      "level": 1,
      "rel_path": "index.html",
      "status": "ok",
      "attempt": 1,
      "diff_ratio": null,
      "message": "无法启动浏览器，跳过视觉对比",
      "output_path": "2026-7-21/index.html"
    },
    {
      "url": "https://zq.titan007.com/analysis/2910807.htm",
      "level": 2,
      "rel_path": "analysis/2910807.htm",
      "status": "ok",
      "attempt": 1,
      "diff_ratio": null,
      "message": "无法启动浏览器，跳过视觉对比",
      "output_path": "2026-7-21/analysis/2910807.htm"
    },
    {
      "url": "https://vip.titan007.com/AsianOdds_n.aspx?id=2910807",
      "level": 2,
      "rel_path": "AsianOdds_n/2910807.html",
      "status": "ok",
      "attempt": 1,
      "diff_ratio": null,
      "message": "无法启动浏览器，跳过视觉对比",
      "output_path": "2026-7-21/AsianOdds_n/2910807.html"
    },
    {
      "url": "https://op1.titan007.com/oddslist/2910807.htm",
      "level": 2,
      "rel_path": "oddslist/2910807.htm",
      "status": "ok",
      "attempt": 1,
      "diff_ratio": null,
      "message": "无法启动浏览器，跳过视觉对比",
      "output_path": "2026-7-21/oddslist/2910807.htm"
    },
    {
      "url": "https://zq.titan007.com/analysis/2929663.htm",
      "level": 2,
      "rel_path": "analysis/2929663.htm",
      "status": "ok",
      "attempt": 1,
      "diff_ratio": null,
      "message": "无法启动浏览器，跳过视觉对比",
      "output_path": "2026-7-21/analysis/2929663.htm"
    },
    {
      "url": "https://vip.titan007.com/AsianOdds_n.aspx?id=2929663",
      "level": 2,
      "rel_path": "AsianOdds_n/2929663.html",
      "status": "ok",
      "attempt": 1,
      "diff_ratio": null,
      "message": "无法启动浏览器，跳过视觉对比",
      "output_path": "2026-7-21/AsianOdds_n/2929663.html"
    },
    {
      "url": "https://op1.titan007.com/oddslist/2929663.htm",
      "level": 2,
      "rel_path": "oddslist/2929663.htm",
      "status": "ok",
      "attempt": 1,
      "diff_ratio": null,
      "message": "无法启动浏览器，跳过视觉对比",
      "output_path": "2026-7-21/oddslist/2929663.htm"
    },
    {
      "url": "https://zq.titan007.com/analysis/2929664.htm",
      "level": 2,
      "rel_path": "analysis/2929664.htm",
      "status": "ok",
      "attempt": 1,
      "diff_ratio": null,
      "message": "无法启动浏览器，跳过视觉对比",
      "output_path": "2026-7-21/analysis/2929664.htm"
    },
    {
      "url": "https://vip.titan007.com/AsianOdds_n.aspx?id=2929664",
      "level": 2,
      "rel_path": "AsianOdds_n/2929664.html",
      "status": "ok",
      "attempt": 1,
      "diff_ratio": null,
      "message": "无法启动浏览器，跳过视觉对比",
      "output_path": "2026-7-21/AsianOdds_n/2929664.html"
    },
    {
      "url": "https://op1.titan007.com/oddslist/2929664.htm",
      "level": 2,
      "rel_path": "oddslist/2929664.htm",
      "status": "ok",
      "attempt": 1,
      "diff_ratio": null,
      "message": "无法启动浏览器，跳过视觉对比",
      "output_path": "2026-7-21/oddslist/2929664.htm"
    },
    {
      "url": "https://zq.titan007.com/analysis/2929665.htm",
      "level": 2,
      "rel_path": "analysis/2929665.htm",
      "status": "ok",
      "attempt": 1,
      "diff_ratio": null,
      "message": "无法启动浏览器，跳过视觉对比",
      "output_path": "2026-7-21/analysis/2929665.htm"
    },
    {
      "url": "https://vip.titan007.com/AsianOdds_n.aspx?id=2929665",
      "level": 2,
      "rel_path": "AsianOdds_n/2929665.html",
      "status": "ok",
      "attempt": 1,
      "diff_ratio": null,
      "message": "无法启动浏览器，跳过视觉对比",
      "output_path": "2026-7-21/AsianOdds_n/2929665.html"
    },
    {
      "url": "https://op1.titan007.com/oddslist/2929665.htm",
      "level": 2,
      "rel_path": "oddslist/2929665.htm",
      "status": "ok",
      "attempt": 1,
      "diff_ratio": null,
      "message": "无法启动浏览器，跳过视觉对比",
      "output_path": "2026-7-21/oddslist/2929665.htm"
    },
    {
      "url": "https://zq.titan007.com/analysis/2999989.htm",
      "level": 2,
      "rel_path": "analysis/2999989.htm",
      "status": "ok",
      "attempt": 1,
      "diff_ratio": null,
      "message": "无法启动浏览器，跳过视觉对比",
      "output_path": "2026-7-21/analysis/2999989.htm"
    },
    {
      "url": "https://vip.titan007.com/AsianOdds_n.aspx?id=2999989",
      "level": 2,
      "rel_path": "AsianOdds_n/2999989.html",
      "status": "ok",
      "attempt": 1,
      "diff_ratio": null,
      "message": "无法启动浏览器，跳过视觉对比",
      "output_path": "2026-7-21/AsianOdds_n/2999989.html"
    },
    {
      "url": "https://op1.titan007.com/oddslist/2999989.htm",
      "level": 2,
      "rel_path": "oddslist/2999989.htm",
      "status": "ok",
      "attempt": 1,
      "diff_ratio": null,
      "message": "无法启动浏览器，跳过视觉对比",
      "output_path": "2026-7-21/oddslist/2999989.htm"
    },
    {
      "url": "https://zq.titan007.com/analysis/2999991.htm",
      "level": 2,
      "rel_path": "analysis/2999991.htm",
      "status": "ok",
      "attempt": 1,
      "diff_ratio": null,
      "message": "无法启动浏览器，跳过视觉对比",
      "output_path": "2026-7-21/analysis/2999991.htm"
    },
    {
      "url": "https://vip.titan007.com/AsianOdds_n.aspx?id=2999991",
      "level": 2,
      "rel_path": "AsianOdds_n/2999991.html",
      "status": "ok",
      "attempt": 1,
      "diff_ratio": null,
      "message": "无法启动浏览器，跳过视觉对比",
      "output_path": "2026-7-21/AsianOdds_n/2999991.html"
    },
    {
      "url": "https://op1.titan007.com/oddslist/2999991.htm",
      "level": 2,
      "rel_path": "oddslist/2999991.htm",
      "status": "ok",
      "attempt": 1,
      "diff_ratio": null,
      "message": "无法启动浏览器，跳过视觉对比",
      "output_path": "2026-7-21/oddslist/2999991.htm"
    },
    {
      "url": "https://zq.titan007.com/analysis/3033092.htm",
      "level": 2,
      "rel_path": "analysis/3033092.htm",
      "status": "ok",
      "attempt": 1,
      "diff_ratio": null,
      "message": "无法启动浏览器，跳过视觉对比",
      "output_path": "2026-7-21/analysis/3033092.htm"
    },
    {
      "url": "https://vip.titan007.com/AsianOdds_n.aspx?id=3033092",
      "level": 2,
      "rel_path": "AsianOdds_n/3033092.html",
      "status": "ok",
      "attempt": 1,
      "diff_ratio": null,
      "message": "无法启动浏览器，跳过视觉对比",
      "output_path": "2026-7-21/AsianOdds_n/3033092.html"
    },
    {
      "url": "https://op1.titan007.com/oddslist/3033092.htm",
      "level": 2,
      "rel_path": "oddslist/3033092.htm",
      "status": "ok",
      "attempt": 1,
      "diff_ratio": null,
      "message": "无法启动浏览器，跳过视觉对比",
      "output_path": "2026-7-21/oddslist/3033092.htm"
    }
  ],
  "elapsed_seconds": 157.17
}